datolite/__init__.py
datolite/__main__.py
datolite/assembler/__init__.py
datolite/assembler/assembler.py
datolite/disassembler/__init__.py
datolite/disassembler/disas.py
datolite/logger/__init__.py
datolite/logger/logger.py
datolite/parser/__init__.py
datolite/parser/parser.py
datolite/patcher/__init__.py
datolite/patcher/patcher.py
datolite-1.0.6.dist-info/METADATA
datolite-1.0.6.dist-info/WHEEL
datolite-1.0.6.dist-info/entry_points.txt
datolite-1.0.6.dist-info/top_level.txt
datolite-1.0.6.dist-info/RECORD
