Metadata-Version: 2.1
Name: datolite
Version: 1.0.6
Summary: Complete Binary Patcher
Author-email: utcq <utcq@waifu.club>
Project-URL: Homepage, https://gitlab.com/utcq/datolite
Keywords: binary,reverse engineering,C,patching,PE,ELF,disassembly,binary analysis
Classifier: License :: OSI Approved :: MIT License
Classifier: Programming Language :: Python
Classifier: Programming Language :: Python :: 3.12
Requires-Python: >=3.9
Requires-Dist: keystone-engine ==0.9.2
Requires-Dist: lief ==0.15.1
